LICENSE
README.md
setup.py
cloudns_sdk/__init__.py
cloudns_sdk/api.py
cloudns_sdk/cloud.py
cloudns_sdk/dnssec.py
cloudns_sdk/exceptions.py
cloudns_sdk/failover.py
cloudns_sdk/geodns.py
cloudns_sdk/groups.py
cloudns_sdk/mail.py
cloudns_sdk/notes.py
cloudns_sdk/notification.py
cloudns_sdk/parked.py
cloudns_sdk/rate_limit.py
cloudns_sdk/records.py
cloudns_sdk/slave.py
cloudns_sdk/ssl.py
cloudns_sdk/stats.py
cloudns_sdk/transfer.py
cloudns_sdk/utils.py
cloudns_sdk/validations.py
cloudns_sdk/zone.py
cloudns_sdk.egg-info/PKG-INFO
cloudns_sdk.egg-info/SOURCES.txt
cloudns_sdk.egg-info/dependency_links.txt
cloudns_sdk.egg-info/requires.txt
cloudns_sdk.egg-info/top_level.txt