Metadata-Version: 2.1
Name: cloudns_sdk
Version: 0.1.0
Summary: A Python SDK for the ClouDNS API
Home-page: https://github.com/lively-ops/cloudns_sdk
Author: Komal Paudyal
Author-email: komal.paudyal@icloud.com
Classifier: Programming Language :: Python :: 3
Classifier: License :: OSI Approved :: MIT License
Classifier: Operating System :: OS Independent
Requires-Python: >=3.6
License-File: LICENSE
Requires-Dist: requests
